oqs/__init__.py
oqs/built_in_functions.py
oqs/engine.py
oqs/errors.py
oqs/interpreter.py
oqs/nodes.py
oqs/parser.py
oqs/constants/__init__.py
oqs/constants/types.py
oqs/constants/values.py
oqs/utils/__init__.py
oqs/utils/checks.py
oqs/utils/classes.py
oqs/utils/conversion.py
oqs/utils/shortcuts.py
oqs-0.10.2.dist-info/METADATA
oqs-0.10.2.dist-info/WHEEL
oqs-0.10.2.dist-info/top_level.txt
oqs-0.10.2.dist-info/RECORD
