Metadata-Version: 2.1
Name: oqs
Version: 0.10.2
Summary: OQS (Open Quick Script) is a Python library for interpreting versatile expressions, supporting basic to advanced operations, custom functions, and performance monitoring. It efficiently handles fundamental types and operations, interprets expressions using variables from dictionaries or JSON, and adheres to robust error handling standards. OQS enhances Python's expression evaluation capabilities, making it ideal for diverse applications.
Home-page: https://github.com/Infuzu/OQS
Author: Infuzu
Author-email: oqs@infuzu.com
License: Creative Commons Attribution 4.0 International License
Classifier: Programming Language :: Python :: 3
Classifier: Operating System :: OS Independent
Requires-Python: >=3.10
License-File: ../LICENSE.md
